yandex_tts_free/__init__.py
yandex_tts_free-0.0.5.dist-info/METADATA
yandex_tts_free-0.0.5.dist-info/WHEEL
yandex_tts_free-0.0.5.dist-info/licenses/LICENSE
yandex_tts_free-0.0.5.dist-info/RECORD
