Metadata-Version: 2.3
Name: yandex-tts-free
Version: 0.0.5
Summary: Free use of YandexSpeachKit in Russian language
Project-URL: Homepage, https://github.com/daswer123/xtts-api-server
Project-URL: Bug Tracker, https://github.com/daswer123/xtts-api-server/issues
Author-email: daswer123 <daswerq123@gmail.com>
License-File: LICENSE
Classifier: License :: OSI Approved :: MIT License
Classifier: Operating System :: OS Independent
Classifier: Programming Language :: Python :: 3
Requires-Python: >=3.9
Requires-Dist: ffmpeg-python
Requires-Dist: requests
